setup.py
pyCountdownTimer/InteruptedSleep.py
pyCountdownTimer/Timer.py
pyCountdownTimer/__init__.py
pyCountdownTimer.egg-info/PKG-INFO
pyCountdownTimer.egg-info/SOURCES.txt
pyCountdownTimer.egg-info/dependency_links.txt
pyCountdownTimer.egg-info/top_level.txt
test/TestInteruptibleCountdownTimer.py
test/__init__.py