Metadata-Version: 1.1
Name: pyCountdownTimer
Version: 1.0
Summary: A count-down timer that periodically checks a flag (to terminate the timer) using a supplied callable.
Home-page: https://github.com/sys-git/pyCountdownTimer
Author: Francis Horsman
Author-email: francis.horsman@gmail.com
License: GNU General Public License
Platform: UNKNOWN
Classifier: Development Status :: 4 - Beta
Classifier: Intended Audience :: Developers
Classifier: License :: OSI Approved :: GNU General Public License v3 (GPLv3)
Classifier: Operating System :: OS Independent
Classifier: Programming Language :: Python
Classifier: Topic :: Communications
